packone/__init__.py
packone/__main__.py
packone/packone.py
packone-0.1.dist-info/DESCRIPTION.rst
packone-0.1.dist-info/LICENSE.txt
packone-0.1.dist-info/METADATA
packone-0.1.dist-info/RECORD
packone-0.1.dist-info/WHEEL
packone-0.1.dist-info/metadata.json
packone-0.1.dist-info/top_level.txt
