Metadata-Version: 2.0
Name: packone
Version: 0.1
Summary: A package to test everything is working.
Home-page: UNKNOWN
Author: UNKNOWN
Author-email: UNKNOWN
License: UNKNOWN
Platform: UNKNOWN
